{
  "parent": "minecraft:recipes/root",
  "criteria": {
    "has_sugar_cane": {
      "conditions": {
        "items": [
          {
            "items": [
              "minecraft:sugar_cane"
            ]
          }
        ]
      },
      "trigger": "minecraft:inventory_changed"
    },
    "has_the_recipe": {
      "conditions": {
        "recipe": "minecraft:sugarcrete_bricks"
      },
      "trigger": "minecraft:recipe_unlocked"
    },
    "has_wheat": {
      "conditions": {
        "items": [
          {
            "items": [
              "minecraft:wheat"
            ]
          }
        ]
      },
      "trigger": "minecraft:inventory_changed"
    }
  },
  "requirements": [
    [
      "has_sugar_cane",
      "has_wheat",
      "has_the_recipe"
    ]
  ],
  "rewards": {
    "recipes": [
      "minecraft:sugarcrete_bricks"
    ]
  },
  "sends_telemetry_event": false
}